LICENSE
MANIFEST.in
README.md
requirements.txt
setup.py
suprabackup/__init__.py
suprabackup.egg-info/PKG-INFO
suprabackup.egg-info/SOURCES.txt
suprabackup.egg-info/dependency_links.txt
suprabackup.egg-info/entry_points.txt
suprabackup.egg-info/requires.txt
suprabackup.egg-info/top_level.txt
suprabackup/cli/__init__.py
suprabackup/cli/db.py
suprabackup/cli/host.py
suprabackup/cli/schedule.py
suprabackup/config/__init__.py
suprabackup/config/config.py
suprabackup/config/defaults.py
suprabackup/db/__init__.py
suprabackup/logging/__init__.py
suprabackup/models/__init__.py
suprabackup/models/base.py
suprabackup/models/host.py
suprabackup/models/job.py
suprabackup/models/schedule.py
suprabackup/scripts/__init__.py
suprabackup/scripts/purge.py
suprabackup/scripts/receive.py
suprabackup/scripts/send.py
suprabackup/scripts/shell.py
suprabackup/scripts/verify.py
suprabackup/server/__init__.py
suprabackup/server/purge.py
suprabackup/server/receive.py
suprabackup/server/verify.py