Metadata-Version: 1.1
Name: suprabackup
Version: 0.3.2
Summary: Suprabackup is a tool to automate xtrabackup database backups
Home-page: https://github.com/quanta-computing/suprabackup
Author: Matthieu 'Korrigan' Rosinski
Author-email: mro@quanta-computing.com
License: MIT
Platform: UNKNOWN
Classifier: Development Status :: 3 - Alpha
Classifier: Programming Language :: Python
Classifier: License :: OSI Approved :: MIT License
Classifier: Topic :: Database
Classifier: Topic :: System :: Archiving :: Backup
